ape_template/__init__.py
ape_template/_cli.py
ape_template/py.typed
ape_template/version.py
ape_template-0.8.0.dist-info/LICENSE
ape_template-0.8.0.dist-info/METADATA
ape_template-0.8.0.dist-info/WHEEL
ape_template-0.8.0.dist-info/entry_points.txt
ape_template-0.8.0.dist-info/top_level.txt
ape_template-0.8.0.dist-info/RECORD
