Metadata-Version: 2.1
Name: ape-template
Version: 0.8.0
Summary: ape-template: ape plugin for cookiecutter based templates
Home-page: https://github.com/ApeWorX/ape-template
Author: ApeWorX Ltd.
Author-email: admin@apeworx.io
License: Apache-2.0
Keywords: ethereum
Classifier: Development Status :: 5 - Production/Stable
Classifier: Intended Audience :: Developers
Classifier: License :: OSI Approved :: Apache Software License
Classifier: Natural Language :: English
Classifier: Operating System :: MacOS
Classifier: Operating System :: POSIX
Classifier: Programming Language :: Python :: 3
Classifier: Programming Language :: Python :: 3.9
Classifier: Programming Language :: Python :: 3.10
Classifier: Programming Language :: Python :: 3.11
Classifier: Programming Language :: Python :: 3.12
Requires-Python: >=3.9,<4
Provides-Extra: test
Provides-Extra: lint
Provides-Extra: release
Provides-Extra: dev
License-File: LICENSE
